{
  "source_path": "/Users/workspace/DevelopProjects/ccb-v0.378/knowledge_base/global/domain/bidding/基础资料/资质/资质证书/资质证书/长城科技(下属公司)/湖南长城/①质量管理体系认证证书.pdf",
  "domain": "management",
  "created_at": "2026-03-05T23:01:15.301355",
  "template": {
    "doc_type": "pdf",
    "sections": [],
    "placeholders": [],
    "template_excerpt": "副本\n辰量管理体系汰迂江事\n滋江明\n湖南長城汁算机票 公 司\n統一社会信用代口:9143021l MA4Ll KR051\n地址:湖南省株洲市天元区湘芸中路天易科技城湖南夭城工上国\n管理体 系符合\nGB/719001-2016/1S09001:2015\n本涯事覆蓋疱国\n平板FL脳 、台式屯脳、宅泥本屯脳、服努器、昆示終端一体机的研友、\n生声和服努 ;PCBA的狙装\n初次汰IIE日 期 2023年H月 29日 本次友江日期:2023年 H月 2?日\n:\n有 数 期 2023年H月 29日 至2026年 H月 28日\n:\n涯 事 号 04523Q31149RONI\n:\nも ジ\n8¨\n荻江姐須在通事有数期内須毎年至少接受一次監督申核,井与管理体系汰江監督結詮通知事一井使用方力有数\n注:管理体系決柾申核報告和盗督結稔通知事在航星決江客声美系管理系銃 (岡址lvip競qc.cn)上荻取\n本江事信息可在国家汰江汰可監督管理委員会官方回靖 (郵w ou.gOvicn〉 和 ∞ぶ彎‐和転岬h甲卸上査洵\n…\n北京大随航星康量決涯中心股倫有限公司\n地址:北京市海淀区玉泉路甲12号七展\n(COPY)\nCertificate of\nManagement Systel□[Certification\nThis is to certify the quality management system of\nHUNAN GREATWALL COⅣ IPUTER SYSTEM CO。\n,LTD.\nunirled sOcial Credit Code:9143021lⅣ IA4LlKR051\nADDRESS:HUNAN GREATWALLINDUSTRIAL PARK,TIANYISCIENCE AND TECHNOLOGY CITχ\nXIANGYUN MIDDIE ROAD,Tひ い■υ AN DISTRICT,ZHUZHOU,HUNAN PROVINCE\nIs in conformity with\nGB/T19001-2016/1S09001:2015\nThis certirlcate covers the fo1lovving area\nDEVELOPⅣIEN■ PRODUCT10N AND SERⅥCE OF TABLET PC,DESKTOP\nPC,LAPTOR SERVERAND DISPLAY TERIIINALALL― IN-ONE MACⅡINE;\nPCBAASSEMBLY\nInitial Certiflcation Date:NOヽ129,2023 Issue Date:From NC)｀Й29,2023\nVllidiけ PeriOd:From NOV29,2023 To NOV28,2026\nCertiflcate No.:04523Q31149ROPI\nY咄\n猾 ∞\n⌒ 中"
  }
}
