{
  "source_path": "/Users/workspace/DevelopProjects/ccb-v0.378/knowledge_base/global/domain/bidding/基础资料/产品资料/终端部材料/02-终端整机资料/0207-X86台式终端/世恒D65Y 所有资料/世恒D65Y-15L-2024010901615096_CCC（中）15L.pdf",
  "domain": "technical",
  "created_at": "2026-03-05T21:15:25.125970",
  "template": {
    "doc_type": "pdf",
    "sections": [],
    "placeholders": [],
    "template_excerpt": "证书编号：2024010901615096\n认证委托人名称及地址\n中国长城科技集团股份有限公司\n深圳市南山区科技园长城计算机大厦\n生产者名称及地址\n中国长城科技集团股份有限公司\n深圳市南山区科技园长城计算机大厦\n生产企业名称及地址\n湖南长城计算机系统有限公司\n湖南省株洲市天元区湘芸中路天易科技城湖南长城工业园\n产品名称和系列、型号、规格\n微型计算机\n世恒 D65Y*******、俊杰*******、世恒*******、Novo*******、凌云*******（*\n均可取值 a-z 或 A-Z 或 0-9 或空或-，代表外观颜色不同，操作系统不同，硬盘、\n内存的容量不同；因市场策略不同而型号命名不同，不影响安全和电磁兼容性能）：\n180-240V～，50Hz，3A\n产品标准和技术要求\nGB 17625.1-2022;GB 4943.1-2022;GB/T 9254.1-2021\n上述产品符合《强制性产品认证实施规则 电子产品及安全附件》\n（CNCA-C09-01:2023）的要求，特发此证。\n发证日期：2024 年 03 月 22 日 有效期至：2027 年 12 月 13 日\n证书信息和有效性可扫描下方二维码或登录发证机构网站查验，\n也可在认监委网站（www.cnca.gov.cn）查询。\n经中国合格评定国家认可委员会认可 CNAS C001-P\n签发："
  }
}
