{
  "source_path": "/Users/workspace/DevelopProjects/ccb-v0.378/knowledge_base/global/domain/bidding/基础资料/产品资料/终端部材料/02-终端整机资料/0201-飞腾终端/020102-通用终端/世恒TD120A2 所有资料/世恒TD120A2节能证书 1  CQC21701283761_0 (1).pdf",
  "domain": "technical",
  "created_at": "2026-03-05T21:53:46.969020",
  "template": {
    "doc_type": "pdf",
    "sections": [],
    "placeholders": [],
    "template_excerpt": "证书编号：CQC21701283761 发证日期：2024年07月18日\n有效期至：2026年01月20日\n委托人名称 中国长城科技集团股份有限公司\n及注册地址 深圳市南山区科技园长城计算机大厦\n品牌 Great Wall长城\n制造商名称 中国长城科技集团股份有限公司\n及注册地址 深圳市南山区科技园长城计算机大厦\n生产企业名称 湖南长城计算机系统有限公司\n及生产地址 湖南省株洲市天元区湘芸中路天易科技城湖南长城工业园\n产品名称和系列、 台式微型计算机\n具体型号见附件，能效等级: 1级\n规格、型号\n产品标准和技术要求 GB 28380-2012\n认证模式 产品检验+初始工厂检查+获证后监督\n上述产品符合 CQC31-045201-2012 认证规则的要求，特此发证。\n本证书为变更证书，证书首次颁发日期：2021年01月21日\n证书有效期内本证书的有效性依据发证机构的定期监督获得保持。\n经中国合格评定国家认可委员会认可CNAS C001-P\n可通过扫描下方二维码或登录国家认监委网站（www.cnca.gov.cn）查验证书信息\n签发：\n证书编号：CQC21701283761 第1页 /共2页\n本证书及附件应同时使用，信息查验说明见证书页 纸号：\n世恒 TD120A2;世恒 TD120A2-003;世恒 TD120A2-004;世恒 TD120A2-005;世恒 TD120A2-006;世恒\nTD120A2-007;世恒 TD120A2-009;世恒 TD120A2-010;世恒 TD120A2-011;世恒 TD120A2-013;世恒\nTD120A2-017;世恒 TD120A2-018;世恒 TD120A2-019;世恒 TD120A2-020;世恒 TD120A2-021;世恒\nTD120A2-023;世恒 TD120A2-025;世恒 TD120A2-027;世恒 TD120A2-037;世恒 TD120A2-039;世恒\nTD120A2-041;世恒 TD120A2-051;世恒 TD120A2-053;世恒 TD120A2-055;世恒 TD120A2-061;世恒\nTD120A2-062;世恒 TD120A2-063;世恒 TD120A2-064;世恒 TD120A2-065;世恒 TD120A2-067;世恒\nTD120A2-069;世恒 TD120A2-071;世恒 TD120A2-075;世恒 TD120A2-076;世恒 TD120A2-077;世恒\nTD120A2-078;世恒 TD120A2-079;世恒 TD120A2-081;世恒 TD120A2-083;世恒 TD120A2-085;世恒\nTD120A2-089;世恒 TD120A2-090;世恒 TD120A2-091;世恒 TD120A2-092;世恒 TD120A2-093;"
  }
}
