{
  "source_path": "/Users/workspace/DevelopProjects/ccb-v0.378/knowledge_base/global/domain/bidding/基础资料/产品资料/终端部材料/02-终端整机资料/0201-飞腾终端/020101-专用终端/世恒ZD120A2 所有资料/世恒Z_节能证书3 CQC22701328018_0.pdf",
  "domain": "technical",
  "created_at": "2026-03-05T21:22:38.333825",
  "template": {
    "doc_type": "pdf",
    "sections": [],
    "placeholders": [],
    "template_excerpt": "证书编号：CQC22701328018 发证日期：2023年06月09日\n有效期至：2026年02月01日\n委托人名称 深圳中电长城信息安全系统有限公司\n及注册地址 深圳市南山区粤海街道科技园社区科发路3号 长城科技大厦401\n品牌 Great Wall长城\n制造商名称 深圳中电长城信息安全系统有限公司\n及注册地址 深圳市南山区粤海街道科技园社区科发路3号 长城科技大厦401\n生产企业名称 中国长城科技集团股份有限公司石岩分公司\n及生产地址 深圳市宝安区石岩镇宝石东路长城电脑工业园\n产品名称和系列、 台式微型计算机\n具体型号见附件，能效等级: 1级\n规格、型号\n产品标准和技术要求 GB 28380-2012\n认证模式 产品检验+初始工厂检查+获证后监督\n上述产品符合 CQC31-045201-2012 认证规则的要求，特此发证。\n本证书为变更证书，证书首次颁发日期：2022年01月10日\n证书有效期内本证书的有效性依据发证机构的定期监督获得保持。\n经中国合格评定国家认可委员会认可CNAS C001-P\n可通过扫描下方二维码或登录国家认监委网站（www.cnca.gov.cn）查验证书信息\n签发：\n证书编号：CQC22701328018 第1页 共2页\n本证书及附件应同时使用，信息查验说明见证书页 纸号：\n型号：世恒 ZD120A2-625、世恒 ZD120A2-626、世恒 ZD120A2-627、世恒 ZD120A2-628、世恒\nZD120A2-629、世恒ZD120A2-630、世恒ZD120A2-631、世恒ZD120A2-632、世恒ZD120A2-633、\n世恒ZD120A2-634、世恒ZD120A2-635、世恒ZD120A2-636、世恒ZD120A2-637、世恒ZD120A2-638、\n世恒ZD120A2-639、世恒ZD120A2-640、世恒ZD120A2-641、世恒ZD120A2-642、世恒ZD120A2-643、\n世恒ZD120A2-644、世恒ZD120A2-645、世恒ZD120A2-646、世恒ZD120A2-647、世恒ZD120A2-648、\n世恒ZD120A2-649、世恒ZD120A2-650、世恒ZD120A2-651、世恒ZD120A2-652、世恒ZD120A2-653、\n世恒ZD120A2-654、世恒ZD120A2-655、世恒ZD120A2-656、世恒ZD120A2-657、世恒ZD120A2-658、\n世恒ZD120A2-659、世恒ZD120A2-660、世恒ZD120A2-661、世恒ZD120A2-662、世恒ZD120A2-663、\n世恒ZD120A2-664、世恒ZD120A2-665、世恒ZD120A2-666、世恒ZD120A2-667、世恒ZD120A2-668、\n世恒ZD120"
  }
}
