{
  "source_path": "/Users/workspace/DevelopProjects/ccb-v0.378/knowledge_base/global/domain/bidding/基础资料/产品资料/服务器产品投标知识库/0101-鲲鹏服务器/010102-RK6260 V5产品资料/擎天RK5260 V5&擎天RK6260 V5 通用服务器 _用户手册_V1.1.pdf",
  "domain": "bidding",
  "created_at": "2026-03-05T22:52:03.140303",
  "template": {
    "doc_type": "pdf",
    "sections": [
      "3.1 物理结构....................................................................................................11",
      "3.2 逻辑结构...................................................................................................13",
      "3.3 组件...........................................................................................................14",
      "3.3.1 前面板组件.............................................................................14",
      "3.3.2 前面板指示灯和按钮...............................................................15",
      "3.3.3 后面板组件.............................................................................17",
      "3.3.4 后面板指示灯..........................................................................19",
      "3.3.5 灵活IO卡...............................................................................20",
      "3.3.6 硬盘编号.................................................................................21",
      "3.3.7 SAS/SATA硬盘指示灯............................................................24",
      "3.3.8 NVMe硬盘指示灯...................................................................24",
      "3.4 PCIe插槽和Riser卡.................................................................................25",
      "3.5 风扇...........................................................................................................31",
      "3.6 技术规格...................................................................................................32",
      "3.7 环境规格...................................................................................................36",
      "3.8 物理规格...................................................................................................39",
      "3.9 电源规格...................................................................................................39",
      "4.1 物理结构...................................................................................................41",
      "4.2 逻辑结构...................................................................................................43",
      "4.3 硬件描述...................................................................................................44",
      "4.3.1 前面板.....................................................................................44",
      "4.3.2 后面板.....................................................................................47",
      "4.4 基础计算机组件........................................................................................49",
      "4.4.1 基础板接口介绍......................................................................49",
      "4.4.2 内存........................................................................................50",
      "4.5 系统扩展组件............................................................................................54",
      "4.6 散热组件...................................................................................................55",
      "4.6.1 风扇板.....................................................................................55",
      "4.6.2 风扇........................................................................................55",
      "4.7 存储组件...................................................................................................57"
    ],
    "placeholders": [
      "1",
      "2",
      "3",
      "]将其括起来，而IPv4地址无此限制。例如：“[2001::64",
      "{}"
    ],
    "template_excerpt": "长城鲲鹏通用服务器\n擎天 RK5260 V5\n擎天 RK6260 V5\n用户手册\n版本：V1.1\n\n声明\n感谢您选择长城产品。\n本手册的用途在于帮助您正确地使用长城服务器产品（以下简称“本产品”）。\n为了帮助您更好和安全地使用本产品，请您在安装和第一次使用本产品前，务必先认\n真仔细阅读随机配送的所有资料，特别要留意本手册所提及的注意事项。请妥善保管\n本手册，以便日后查阅。\n除了我们提示您可以修改的参数之外，在任何时候，请您不要修改本产品主板BIOS\n中的任何其他参数。\n如果您未按照本手册的指示和要求正确地安装、使用或保管本产品，或是让我们授权\n的技术人员修理、变更本产品，我们将不对由此导致的损害承担任何责任。\n对于您在本产品上使用我们推荐之外的软件，我们对其可靠性不作任何保证。\n对于您将本产品提供的软件使用到其他产品上，我们对其可靠性不作任何保证。\n我们特别提醒您：在使用本产品过程中，请您注意对您的数据进行必要的备份，我们\n对您个人的数据不作任何数据恢复保证。\n本手册中涉及的各软件、硬件产品的标识、名称版权归该产品的相应公司拥有。\n我们已经对本手册进行了仔细的校核，但我们并不能保证本手册完全没有任何错误和\n纰漏。为了更好地为您提供服务，我们可能会对本手册的内容进行改进或修改，恕不\n另行通知。若您在使用本产品过程中发现任何与本手册有不一致的地方，或者您想得\n到最新的信息，亦或是有任何的问题和想法，欢迎致电我们或登录我们的服务网站垂\n询。\n手册内容可能随时变更，恕不另行通知。最新文档请登录官网获取。产品（包括但不\n限于外观、指示灯颜色、产品大小、软件设置等）请以实物为准。\n以上声明中，“我们”指代中国长城科技集团股份有限公司。中国长城科技集团股份\n有限公司拥有对以上声明的最终解释权。\nI\nCopyright©2024中国长城科技集团股份有限公司及其许可者版权所有，保留一切\n权利。\n未经本公司书面许可，任何单位和个人不得擅自摘抄、复制本书内容的部分或全部，\n并不得以任何形式传播。\nII\n前言\n概述\n本文档介绍了擎天RK5260V5和擎天RK6260V5长城鲲鹏通用服务器的产品外观，\n结构，组件和规格，指导用户对服务器进行安装、连线、上电下电、基本配置、安装\n操作系统及处理故障等操作。\n读者对象\n本手册主要适用于以下工程师：\n 技术支持工程师\n 渠道伙伴技术支持工程师\n 企业管理员\n符号约定\n符号 提示事项\n表示如不避免则将会导致死亡或严重伤害的具有高等级风险的危害。\n表示如不避免则可能导致死亡或严重伤害的具有中等级风险的危害。\n表示如不避免则可能导致轻微或中度伤害的具有低等级风险的危害。\n用于传递设备或环境安全警示信息。如不避免则可能会导致设备损坏、数据丢\n失、设备性能降低或其它不可预知的结果。\n“须知”不涉及人身伤害。\n对正文中重点信息的补充说明。\n“说明"
  }
}
