{
  "source_path": "/Users/workspace/DevelopProjects/ccb-v0.378/knowledge_base/global/domain/bidding/基础资料/产品资料/终端部材料/05-产品兼容性互认证明/0501-专用产品配套软件互认证/泛微互认证.pdf",
  "domain": "bidding",
  "created_at": "2026-03-05T22:17:18.483090",
  "template": {
    "doc_type": "pdf",
    "sections": [],
    "placeholders": [
      "f§",
      "f§Jf$: e-nation",
      "f§J~: e-nation"
    ],
    "template_excerpt": "cp\n~~)~±J II E:g *±m{;;J~t~~*~Jtf[~~~PJ Cm i~: *±,BX{;;~)\n~-t5~5z1~~~~§f4t~~~15jf[~~~P:1 cmi~: 121~~~~§) ~9!~irt,\n1~t±i~~ ~~ai-B:\n*±,5XZF722, *±,BXZN 140A2,\n*±,BX{;;~F~: ~1~~\nZA238A2, t!!tsZD120A2, t!!ts\n~f~~ZF711, ~f~~ZF719,\nZF719\n~-t5~5z1~~~~§f41~~~{5j~~~~PJF~: 5z1~~t1J~fm~\n$X1tf:[f§]~: e-cology]V9.o, 5z1~~EgT-lE~~SJZg$X1tf:[f§]~: e\nnationfBJ*go\n*±,5XZN140A2,\n~~...tF~*±,5XZF722, ~f~~ZA238A2, ~f~~\nZF711, t!!tsZD120A2,\n~1~~ZF719, t!!tsZF719i~*ffl~F\n~1tf:fD~Ft*fI=*~Jt, F~'ti~~~IYJ~~r, ~~T~~~PJ~o\n~ j£fil\n~ weaver\n~~J*±J 11 cJ:l ft! ~±mf~,~,~~*;lt~~[{~ PJ ( mif$: ~±mf~~)\n~_t~m;2~~~$xft1=~~~~PJ (f§Jf$: ;2~~~$xft1=) ;91~iit, 1~t±:1~~1'\n~±~o·\n-i::::I J-U •\n140A2,\n~±mf~~F~: ~±mZF722, ~±mZN ~f~~\nZA238A2, tl!tsZD120A2, tl!ts\n~f~~ZF711, ~f~~ZF719,\nzF119 ~_t;m;2~~~$xft1=f[~~~PJF~: ;2~~~t1J~f§J~$xftt=[mi\nf$: e-cology]V9.1, )z~~~ft!T-iE~~S}Zg.$Xft1=[f§Jf$: e-nation]OJ\n~~_tp~~±mZF722, ~±mZN140A2, ~f~~ZA238A2, ~f~~\nZF711, ttttsZD120A2,\n~1~~ZF719, ttttsZF719:t~*ffl~F\n~{t1=fD~Ffif'f=*;Jt F~'tift~~!,PJ~~T' ~~Tt~AEOJ~o\n1\nII cp P:l (\n~~~*±J ~ ~±~f~,1~~l~~.*g;t~~~~ f§J~: ~±~{;;~)\n~k~~~~~w~~&~~~P:J(mJ~:~~~~)ru~,\n1ijt±j~J l';a1~:\n~±~f~~F55: ~~ZF860, ~~ZF720 ~ ~k~ij)z~~~~~§\n~413Z~~1fr~~~~o:JF55: )z~~~t1J~"
  }
}
