{
  "source_path": "/Users/workspace/DevelopProjects/ccb-v0.378/knowledge_base/global/domain/bidding/基础资料/服务资料/售后资料/投标方案/特殊要求服务方案.docx",
  "domain": "technical",
  "created_at": "2026-03-05T21:08:39.044119",
  "template": {
    "doc_type": "docx",
    "sections": [],
    "placeholders": [],
    "template_excerpt": "针对客户的特殊要求，提供定制化、高效、优质的售后服务，确保问题得到及时、有效的解决。提高客户对售后服务的满意度，增强客户对公司产品和品牌的信任和认可，促进业务的持续发展和口碑传播。所有特殊服务涉及费用视具体情况确定。\n设立专门渠道：开通专门的热线电话（4008118888）、邮箱或在线平台，方便客户提交特殊要求的售后服务申请。确保渠道畅通无阻，并提供用户需要的服务时间和响应承诺。\n详细信息记录：客服人员在接到客户申请后，立即详细记录客户的基本信息（包括姓名、联系方式、购买产品信息等）、特殊要求的具体内容（如维修的紧急程度、特殊的维修工艺、特定的时间限制等）以及客户期望的解决时间和方式等信息。\n初步评估与分类：客服人员将收集到的信息提交给技术专家团队进行初步评估，确定客户特殊要求的可行性和所需资源。根据评估结果，将服务申请分为紧急、一般和复杂三类，以便制定相应的服务计划和优先级排序。\n制定个性化方案：针对不同类型的服务申请，专项负责人组织技术专家团队和客服团队共同制定个性化的售后服务方案。方案应包括具体的服务步骤、预计完成时间、所需的人力、物力和技术支持等详细信息，并明确各环节的责任人。\n与客户沟通确认：客服人员将制定好的服务方案及时反馈给客户，详细解释方案的内容和实施步骤，确保客户理解并认可。对于客户提出的疑问和意见，及时进行调整和优化，直至客户满意为止。同时，与客户明确服务过程中的沟通方式和时间节点，确保客户能够随时了解服务进展情况。\n资源调配与准备：根据服务方案，专项负责人迅速调配所需的人力、物力和技术资源，确保各项准备工作就绪。技术专家团队提前对可能出现的技术难题进行预研和解决方案制定，维修人员准备好相应的工具和配件，客服人员与客户保持密切沟通，提前协调好上门服务的时间和地点等事宜。\n现场服务执行：维修人员按照服务方案的要求，准时到达客户指定地点进行现场服务。在服务过程中，严格遵守操作规范和安全标准，确保服务质量和效率。技术专家团队根据实际情况提供远程或现场技术支持，协助维修人员解决遇到的复杂问题。客服人员及时跟进服务进展情况，每隔24小时向客户反馈一次服务状态，如已完成的工作步骤、预计剩余时间等，让客户心中有数。\n质量监控与反馈：设立质量监控岗位，对服务实施过程进行全程监督和检查。定期对服务质量进行评估和分析，及时发现和纠正存在的问题。维修人员在完成每一项服务任务后，填写详细的服务报告，包括服务内容、使用的配件、解决的问题以及客户的满意度评价等信息，提交给质量监控人员审核和存档。\n满意度回访调查：客服人员在服务完成后的5天内，对客户进行满意度回访调查。通过电话、邮件或在线问卷等方式，了解客户对整个售后服务过程的满意度评价，包括服务态度、服务效率、技术水平、问题解决程度等方面。认真倾听客户的意见和建议，对于客户提出的不满意之处，详细记录并制定改进措施，"
  }
}
