{
  "source_path": "/Users/workspace/DevelopProjects/ccb-v0.378/knowledge_base/global/domain/bidding/基础资料/人员资质/职称类/副高/高级工程师   解超.pdf",
  "domain": "bidding",
  "created_at": "2026-03-05T21:08:00.084887",
  "template": {
    "doc_type": "pdf",
    "sections": [],
    "placeholders": [],
    "template_excerpt": "山东省高级职称证书\n本证书表明持证人具有相应学术技术水平和专业能力\n姓 名：解超\n性 别：男\n从事专业：电子信息\n系列（专业）名称：工程技术\n资格名称：高级工程师\n评审时间：2023年03月22日\n评审委员会： 济南市工程技术职务高级评审委员会\n身份证号：\n371312198606025513\n证书编号：鲁220100033200500\n公布文号：济人社发〔2023〕4号\n证书查询：山东省专业技术人员管理服务平台\n（http://hrss.shandong.gov.cn/rsrc/zcps）\n在线验证码：U80913AK\n核准公布部门（章）\n公布时间：2023年04月19日"
  }
}
